vcard_graph/__init__.py
vcard_graph/cli.py
vcard_graph/graph.py
vcard_graph/parser.py
vcard_graph-0.1.0.dist-info/licenses/LICENSE
vcard_graph-0.1.0.dist-info/METADATA
vcard_graph-0.1.0.dist-info/WHEEL
vcard_graph-0.1.0.dist-info/entry_points.txt
vcard_graph-0.1.0.dist-info/top_level.txt
vcard_graph-0.1.0.dist-info/RECORD
